rustground
