Metadata-Version: 2.1
Name: rustground
Version: 0.0.4
Summary: My short description for my project.
Home-page: https://github.com/franceme/rustground
Author: Miles Frantz
Author-email: frantzme@vt.edu
License: UNKNOWN
Platform: UNKNOWN
Classifier: Programming Language :: Python
Classifier: Programming Language :: Python :: 3
Requires-Python: >=3.8.0
License-File: LICENSE
